spreadsheet_intelligence/__init__.py
spreadsheet_intelligence/converters/__init__.py
spreadsheet_intelligence/converters/drawing/__init__.py
spreadsheet_intelligence/converters/drawing/drawing_raw_converters/__init__.py
spreadsheet_intelligence/converters/drawing/drawing_raw_converters/base_drawing_raw_converter.py
spreadsheet_intelligence/converters/drawing/drawing_raw_converters/connector_raw_converter.py
spreadsheet_intelligence/converters/drawing/drawing_raw_converters/shape_raw_converter.py
spreadsheet_intelligence/core/__init__.py
spreadsheet_intelligence/core/base_loader.py
spreadsheet_intelligence/core/excel_autoshape_loader.py
spreadsheet_intelligence/formatters/__init__.py
spreadsheet_intelligence/formatters/drawing/__init__.py
spreadsheet_intelligence/formatters/drawing/format.py
spreadsheet_intelligence/models/__init__.py
spreadsheet_intelligence/models/common/__init__.py
spreadsheet_intelligence/models/common/common_data.py
spreadsheet_intelligence/models/common/enums.py
spreadsheet_intelligence/models/converted/__init__.py
spreadsheet_intelligence/models/converted/base_models.py
spreadsheet_intelligence/models/converted/drawing_models.py
spreadsheet_intelligence/models/raw/__init__.py
spreadsheet_intelligence/models/raw/drawing/__init__.py
spreadsheet_intelligence/models/raw/drawing/anchor_models.py
spreadsheet_intelligence/models/raw/drawing/base_models.py
spreadsheet_intelligence/models/raw/drawing/drawing_models.py
spreadsheet_intelligence/models/raw/theme/__init__.py
spreadsheet_intelligence/models/raw/theme/theme_models.py
spreadsheet_intelligence/parsers/__init__.py
spreadsheet_intelligence/parsers/abstract/__init__.py
spreadsheet_intelligence/parsers/abstract/base_parser.py
spreadsheet_intelligence/parsers/abstract/base_xml_parser.py
spreadsheet_intelligence/parsers/common/__init__.py
spreadsheet_intelligence/parsers/common/common_parser.py
spreadsheet_intelligence/parsers/drawing/__init__.py
spreadsheet_intelligence-0.1.0.dist-info/licenses/LICENCE
spreadsheet_intelligence-0.1.0.dist-info/METADATA
spreadsheet_intelligence-0.1.0.dist-info/WHEEL
spreadsheet_intelligence-0.1.0.dist-info/top_level.txt
spreadsheet_intelligence-0.1.0.dist-info/RECORD
